{
  "version": 1,
  "size": [
    16,
    16,
    16
  ],
  "palette": [
    "#ebebeb",
    "#ff9300",
    "#ff2600",
    "#ffc677",
    "#aa7942",
    "#422703",
    "#000000",
    "#1d3557",
    "#ff6b6b",
    "#ffd93d",
    "#6bcb77",
    "#4d96ff",
    "#b983ff",
    "#ff4d6d",
    "#9ef01a",
    "#00f5d4"
  ],
  "voxels": [
    "3a05",
    "2913",
    "3913",
    "4913",
    "2a13",
    "3a13",
    "4a13",
    "2923",
    "3923",
    "4923",
    "2a23",
    "3a23",
    "4a23",
    "1834",
    "2834",
    "3834",
    "4834",
    "5834",
    "1934",
    "2934",
    "3934",
    "4934",
    "5934",
    "1a34",
    "2a34",
    "3a34",
    "4a34",
    "5a34",
    "1b34",
    "2b36",
    "3b34",
    "4b36",
    "5b34",
    "1c34",
    "2c34",
    "3c34",
    "4c34",
    "5c34",
    "1844",
    "2844",
    "3844",
    "4844",
    "5844",
    "1944",
    "2944",
    "3944",
    "4944",
    "5944",
    "1a44",
    "2a44",
    "3a44",
    "4a44",
    "5a44",
    "0b45",
    "1b45",
    "2b44",
    "3b44",
    "4b44",
    "5b45",
    "6b45",
    "0c45",
    "1c45",
    "2c44",
    "3c44",
    "4c44",
    "5c45",
    "6c45",
    "0d45",
    "1d45",
    "5d45",
    "6d45",
    "0055",
    "1055",
    "5055",
    "6055",
    "0154",
    "1154",
    "5154",
    "6154",
    "0254",
    "1254",
    "5254",
    "6254",
    "0354",
    "1354",
    "5354",
    "6354",
    "0454",
    "1454",
    "2453",
    "3453",
    "4453",
    "5454",
    "6454",
    "0554",
    "1554",
    "2554",
    "3554",
    "4554",
    "5554",
    "6554",
    "0654",
    "1654",
    "2654",
    "3654",
    "4654",
    "5654",
    "6654",
    "0754",
    "1754",
    "2754",
    "3754",
    "4754",
    "5754",
    "6754",
    "0854",
    "1854",
    "2854",
    "3854",
    "4854",
    "5854",
    "6854",
    "1954",
    "2954",
    "3954",
    "4954",
    "5954",
    "1a54",
    "2a54",
    "3a54",
    "4a54",
    "5a54",
    "0b55",
    "1b54",
    "2b54",
    "3b54",
    "4b54",
    "5b54",
    "6b55",
    "0c55",
    "1c54",
    "2c54",
    "3c54",
    "4c54",
    "5c54",
    "6c55",
    "0d55",
    "1d55",
    "5d55",
    "6d55",
    "0065",
    "1065",
    "5065",
    "6065",
    "0164",
    "1164",
    "5164",
    "6164",
    "0264",
    "1264",
    "5264",
    "6264",
    "0364",
    "1364",
    "5364",
    "6364",
    "0464",
    "1464",
    "2463",
    "3463",
    "4463",
    "5464",
    "6464",
    "0564",
    "1564",
    "2564",
    "3560",
    "4560",
    "5564",
    "6564",
    "0664",
    "1664",
    "2664",
    "3660",
    "4660",
    "5664",
    "6664",
    "0764",
    "1764",
    "2764",
    "3760",
    "4760",
    "5764",
    "6764",
    "0864",
    "1864",
    "2864",
    "3864",
    "4864",
    "5864",
    "6864",
    "0473",
    "1473",
    "2473",
    "3473",
    "4473",
    "5473",
    "6473",
    "0574",
    "1574",
    "2574",
    "3570",
    "4570",
    "5574",
    "6574",
    "0674",
    "1674",
    "2674",
    "3670",
    "4670",
    "5674",
    "6674",
    "0774",
    "1774",
    "2774",
    "3770",
    "4770",
    "5774",
    "6774",
    "0874",
    "1874",
    "2874",
    "3874",
    "4874",
    "5874",
    "6874",
    "0483",
    "1483",
    "2483",
    "3483",
    "4483",
    "5483",
    "6483",
    "0584",
    "1584",
    "2584",
    "3580",
    "4580",
    "5584",
    "6584",
    "0684",
    "1684",
    "2684",
    "3680",
    "4680",
    "5684",
    "6684",
    "0784",
    "1784",
    "2784",
    "3780",
    "4780",
    "5784",
    "6784",
    "0884",
    "1884",
    "2884",
    "3884",
    "4884",
    "5884",
    "6884",
    "0493",
    "1493",
    "2493",
    "3493",
    "4493",
    "5493",
    "6493",
    "0594",
    "1594",
    "2594",
    "3590",
    "4590",
    "5594",
    "6594",
    "0694",
    "1694",
    "2694",
    "3690",
    "4690",
    "5694",
    "6694",
    "0794",
    "1794",
    "2794",
    "3790",
    "4790",
    "5794",
    "6794",
    "0894",
    "1894",
    "2894",
    "3894",
    "4894",
    "5894",
    "6894",
    "04a4",
    "14a4",
    "24a3",
    "34a3",
    "44a3",
    "54a4",
    "64a4",
    "05a4",
    "15a4",
    "25a4",
    "35a0",
    "45a0",
    "55a4",
    "65a4",
    "06a4",
    "16a4",
    "26a4",
    "36a0",
    "46a0",
    "56a4",
    "66a4",
    "07a4",
    "17a4",
    "27a4",
    "37a0",
    "47a0",
    "57a4",
    "67a4",
    "08a4",
    "18a4",
    "28a4",
    "38a4",
    "48a4",
    "58a4",
    "68a4",
    "00b5",
    "10b5",
    "50b5",
    "60b5",
    "01b4",
    "11b4",
    "51b4",
    "61b4",
    "02b4",
    "12b4",
    "52b4",
    "62b4",
    "03b4",
    "13b4",
    "53b4",
    "63b4",
    "04b4",
    "14b4",
    "24b3",
    "34b3",
    "44b3",
    "54b4",
    "64b4",
    "05b4",
    "15b4",
    "25b4",
    "35b0",
    "45b0",
    "55b4",
    "65b4",
    "06b4",
    "16b4",
    "26b4",
    "36b0",
    "46b0",
    "56b4",
    "66b4",
    "07b4",
    "17b4",
    "27b4",
    "37b0",
    "47b0",
    "57b4",
    "67b4",
    "08b4",
    "18b4",
    "28b4",
    "38b4",
    "48b4",
    "58b4",
    "68b4",
    "00c5",
    "10c5",
    "50c5",
    "60c5",
    "01c4",
    "11c4",
    "51c4",
    "61c4",
    "02c4",
    "12c4",
    "52c4",
    "62c4",
    "03c4",
    "13c4",
    "53c4",
    "63c4",
    "04c4",
    "14c4",
    "24c3",
    "34c3",
    "44c3",
    "54c4",
    "64c4",
    "05c4",
    "15c4",
    "25c4",
    "35c4",
    "45c4",
    "55c4",
    "65c4",
    "06c4",
    "16c4",
    "26c4",
    "36c4",
    "46c4",
    "56c4",
    "66c4",
    "07c4",
    "17c4",
    "27c4",
    "37c4",
    "47c4",
    "57c4",
    "67c4",
    "08c4",
    "18c4",
    "28c4",
    "38c4",
    "48c4",
    "58c4",
    "68c4",
    "37d5",
    "38d5",
    "39d5",
    "3ad5",
    "3ae5"
  ],
  "regions": {
    "leg-fr": {
      "min": [
        5,
        0,
        5
      ],
      "max": [
        6,
        4,
        6
      ]
    },
    "leg-fl": {
      "min": [
        2,
        0,
        5
      ],
      "max": [
        3,
        4,
        6
      ]
    },
    "leg-rl": {
      "min": [
        2,
        0,
        11
      ],
      "max": [
        3,
        4,
        12
      ]
    },
    "leg-rr": {
      "min": [
        5,
        0,
        11
      ],
      "max": [
        6,
        4,
        12
      ]
    },
    "head": {
      "min": [
        0,
        4,
        1
      ],
      "max": [
        8,
        10,
        4
      ]
    }
  },
  "animations": {
    "anim": {
      "regionName": "leg-fr",
      "loop": true,
      "keyframes": [
        {
          "type": "rotate",
          "from": 0,
          "to": 20,
          "duration": 0.3,
          "pivot": [
            3,
            4,
            6
          ],
          "axis": [
            1,
            0,
            0
          ]
        },
        {
          "type": "rotate",
          "from": 0,
          "to": -40,
          "duration": 0.6,
          "pivot": [
            3,
            4,
            6
          ],
          "axis": [
            1,
            0,
            0
          ]
        },
        {
          "type": "rotate",
          "from": 0,
          "to": 20,
          "duration": 0.3,
          "pivot": [
            3,
            4,
            6
          ],
          "axis": [
            1,
            0,
            0
          ]
        }
      ]
    },
    "anim1": {
      "regionName": "leg-fl",
      "loop": true,
      "keyframes": [
        {
          "type": "rotate",
          "from": 0,
          "to": -20,
          "duration": 0.3,
          "pivot": [
            3,
            4,
            6
          ],
          "axis": [
            1,
            0,
            0
          ]
        },
        {
          "type": "rotate",
          "from": 0,
          "to": 40,
          "duration": 0.6,
          "pivot": [
            3,
            4,
            6
          ],
          "axis": [
            1,
            0,
            0
          ]
        },
        {
          "type": "rotate",
          "from": 0,
          "to": -20,
          "duration": 0.3,
          "pivot": [
            3,
            4,
            6
          ],
          "axis": [
            1,
            0,
            0
          ]
        }
      ]
    },
    "anim11": {
      "regionName": "leg-rl",
      "loop": true,
      "keyframes": [
        {
          "type": "rotate",
          "from": 0,
          "to": 20,
          "duration": 0.3,
          "pivot": [
            3,
            4,
            12
          ],
          "axis": [
            1,
            0,
            0
          ]
        },
        {
          "type": "rotate",
          "from": 0,
          "to": -40,
          "duration": 0.6,
          "pivot": [
            3,
            4,
            12
          ],
          "axis": [
            1,
            0,
            0
          ]
        },
        {
          "type": "rotate",
          "from": 0,
          "to": 20,
          "duration": 0.3,
          "pivot": [
            3,
            4,
            12
          ],
          "axis": [
            1,
            0,
            0
          ]
        }
      ]
    },
    "anim111": {
      "regionName": "leg-rr",
      "loop": true,
      "keyframes": [
        {
          "type": "rotate",
          "from": 0,
          "to": -20,
          "duration": 0.3,
          "pivot": [
            3,
            4,
            12
          ],
          "axis": [
            1,
            0,
            0
          ]
        },
        {
          "type": "rotate",
          "from": 0,
          "to": 40,
          "duration": 0.6,
          "pivot": [
            3,
            4,
            12
          ],
          "axis": [
            1,
            0,
            0
          ]
        },
        {
          "type": "rotate",
          "from": 0,
          "to": -20,
          "duration": 0.3,
          "pivot": [
            3,
            4,
            12
          ],
          "axis": [
            1,
            0,
            0
          ]
        }
      ]
    },
    "anim2": {
      "regionName": "head",
      "loop": true,
      "keyframes": [
        {
          "type": "rotate",
          "from": 0,
          "to": 5,
          "duration": 0.3,
          "pivot": [
            5,
            9,
            6
          ],
          "axis": [
            0,
            0,
            1
          ]
        },
        {
          "type": "rotate",
          "from": 0,
          "to": -10,
          "duration": 0.6,
          "pivot": [
            5,
            9,
            6
          ],
          "axis": [
            0,
            0,
            1
          ]
        },
        {
          "type": "rotate",
          "from": 0,
          "to": 5,
          "duration": 0.3,
          "pivot": [
            5,
            9,
            6
          ],
          "axis": [
            0,
            0,
            1
          ]
        }
      ]
    }
  },
  "emitters": {},
  "groups": {
    "group": {
      "animations": [
        "anim",
        "anim1",
        "anim11",
        "anim111"
      ],
      "emitters": [],
      "guard": null,
      "endState": null
    }
  }
}